lum0x/__init__.py
lum0x/cli.py
lum0x/lum0xhandler.js
lum0x/handlers/__init__.py
lum0x/handlers/credential_handler.py
lum0x/handlers/deploy_handler.py
lum0x/handlers/utils.py
lum0x_cli-0.1.0.dist-info/METADATA
lum0x_cli-0.1.0.dist-info/WHEEL
lum0x_cli-0.1.0.dist-info/entry_points.txt
lum0x_cli-0.1.0.dist-info/top_level.txt
lum0x_cli-0.1.0.dist-info/RECORD
