Metadata-Version: 2.1
Name: lum0x-cli
Version: 0.1.0
Summary: A CLI tool for deploying and managing functions for Lum0x Infrastructure
Author: lum0x
Author-email: dev@lum0x.com
Classifier: Programming Language :: Python :: 3
Classifier: License :: OSI Approved :: MIT License
Classifier: Operating System :: OS Independent
Requires-Python: >=3.10
Requires-Dist: click
Requires-Dist: boto3
Requires-Dist: requests
Requires-Dist: python-dotenv
